alexPlot/__init__.py
alexPlot/example.txt
alexPlot/help.txt
alexPlot/plotting.py
alexPlot/funcs/axes.py
alexPlot/funcs/plot_functions.py
alexPlot/funcs/pulls.py
alexPlot/funcs/useful_functions.py
alexPlot/number_storage/poisson_asym_errors_lookup_table.pickle
alexPlot-1.0.1.dist-info/LICENSE.txt
alexPlot-1.0.1.dist-info/METADATA
alexPlot-1.0.1.dist-info/WHEEL
alexPlot-1.0.1.dist-info/top_level.txt
alexPlot-1.0.1.dist-info/RECORD
