Metadata-Version: 2.1
Name: alexPlot
Version: 1.0.1
Summary: A simple plotting package for use with zfit
Home-page: https://gitlab.cern.ch/amarshal/alexPlot
Author: Alex Marshall
Author-email: alex.marshall@bristol.ac.uk
Classifier: Programming Language :: Python :: 3
Classifier: License :: OSI Approved :: MIT License
Classifier: Operating System :: OS Independent
License-File: LICENSE.txt
